[
  {
    "nameEn": "bear",
    "nameEs": "oso",
    "img": "assetsGuessTheAnimal/img/Bear.png"
  },
  {
    "nameEn": "cat",
    "nameEs": "gato",
    "img": "assetsGuessTheAnimal/img/Cat.png"
  },
  {
    "nameEn": "lion",
    "nameEs": "león",
    "img": "assetsGuessTheAnimal/img/Lion.png"
  },
  {
    "nameEn": "dog",
    "nameEs": "perro",
    "img": "assetsGuessTheAnimal/img/Dog.png"
  },
  {
    "nameEn": "llama",
    "nameEs": "llama",
    "img": "assetsGuessTheAnimal/img/Llama.png"
  },
  {
    "nameEn": "orangutan",
    "nameEs": "orangután",
    "img": "assetsGuessTheAnimal/img/Orangutan.png"
  },
  {
    "nameEn": "snake",
    "nameEs": "serpiente",
    "img": "assetsGuessTheAnimal/img/Snake.png"
  },
  {
    "nameEn": "toucan",
    "nameEs": "tucán",
    "img": "assetsGuessTheAnimal/img/Toucan.png"
  },
  {
    "nameEn": "deer",
    "nameEs": "ciervo",
    "img": "assetsGuessTheAnimal/img/Deer.png"
  },
  {
    "nameEn": "hog",
    "nameEs": "jabalí",
    "img": "assetsGuessTheAnimal/img/Hog.png"
  },
  {
    "nameEn": "zebra",
    "nameEs": "Cebra",
    "img": "assetsGuessTheAnimal/img/Zebra.png"
  },
  {
    "nameEn": "raccon",
    "nameEs": "mapache",
    "img": "assetsGuessTheAnimal/img/Raccon.png"
  },
  {
    "nameEn": "ostrich",
    "nameEs": "avestruz",
    "img": "assetsGuessTheAnimal/img/Ostrich.png"
  },
  {
    "nameEn": "tiger",
    "nameEs": "tigre",
    "img": "assetsGuessTheAnimal/img/Tiger.png"
  },
  {
    "nameEn": "turtle",
    "nameEs": "tortuga",
    "img": "assetsGuessTheAnimal/img/Turtle.png"
  },
  {
    "nameEn": "meerkat",
    "nameEs": "suricata",
    "img": "assetsGuessTheAnimal/img/Meerkat.png"
  },
  {
    "nameEn": "platypus",
    "nameEs": "ornitorrinco",
    "img": "assetsGuessTheAnimal/img/Platypus.png"
  },
  {
    "nameEn": "eagle",
    "nameEs": "águila",
    "img": "assetsGuessTheAnimal/img/Eagle.png"
  },
  {
    "nameEn": "koala",
    "nameEs": "ceagleoala",
    "img": "assetsGuessTheAnimal/img/Koala.png"
  },
  {
    "nameEn": "kangaroo",
    "nameEs": "canguro",
    "img": "assetsGuessTheAnimal/img/Kangaroo.png"
  },
  {
    "nameEn": "cheetah",
    "nameEs": "guepardo",
    "img": "assetsGuessTheAnimal/img/Cheetah.png"
  },
  {
    "nameEn": "rhinoceros",
    "nameEs": "rinoceronte",
    "img": "assetsGuessTheAnimal/img/Rino.png"
  },
  {
    "nameEn": "gorilla",
    "nameEs": "gorilRinoa",
    "img": "assetsGuessTheAnimal/img/Gorilla.png"
  },
  {
    "nameEn": "panda",
    "nameEs": "panda",
    "img": "assetsGuessTheAnimal/img/Panda.png"
  }
]